{"NA1_4306236625": {"time": 1652470810.227, "bot_sums": [[7, 4], [4, 7]], "win_loss": [false, true], "champions": ["Sivir", "Tristana"]}, "NA1_4306320656": {"time": 1652473162.743, "bot_sums": [[4, 1], [4, 7]], "win_loss": [false, true], "champions": ["Lucian", "Tristana"]}, "NA1_4306316565": {"time": 1652475982.065, "bot_sums": [[3, 4], [4, 7]], "win_loss": [false, true], "champions": ["Tristana", "Jhin"]}, "NA1_4306361530": {"time": 1652478082.917, "bot_sums": [[4, 7], [4, 3]], "win_loss": [true, false], "champions": ["Tristana", "Lucian"]}, "NA1_4306377028": {"time": 1652480494.039, "bot_sums": [[14, 4], [4, 7]], "win_loss": [false, true], "champions": ["Seraphine", "Tristana"]}, "NA1_4306454154": {"time": 1652483661.603, "bot_sums": [[4, 7], [4, 7]], "win_loss": [false, true], "champions": ["Ashe", "Tristana"]}, "NA1_4306481643": {"time": 1652486012.648, "bot_sums": [[4, 7], [3, 4]], "win_loss": [true, false], "champions": ["Tristana", "Ezreal"]}, "NA1_4306489288": {"time": 1652488949.976, "bot_sums": [[4, 7], [4, 7]], "win_loss": [true, false], "champions": ["Xayah", "Ezreal"]}, "NA1_4306585927": {"time": 1652491238.2, "bot_sums": [[4, 7], [4, 7]], "win_loss": [false, true], "champions": ["Vayne", "Jinx"]}, "NA1_4307657499": {"time": 1652559893.799, "bot_sums": [[7, 4], [4, 7]], "win_loss": [true, false], "champions": ["Ezreal", "Lucian"]}, "NA1_4307742789": {"time": 1652562741.313, "bot_sums": [[7, 4], [4, 3]], "win_loss": [false, true], "champions": ["Lucian", "Kaisa"]}, "NA1_4307718481": {"time": 1652564478.617, "bot_sums": [[4, 7], [4, 3]], "win_loss": [true, false], "champions": ["Samira", "Ezreal"]}, "NA1_4307960816": {"time": 1652577273.86, "bot_sums": [[4, 7], [4, 7]], "win_loss": [false, true], "champions": ["Ezreal", "Tristana"]}, "NA1_4307977597": {"time": 1652579489.831, "bot_sums": [[4, 7], [4, 7]], "win_loss": [false, true], "champions": ["Ezreal", "Lucian"]}, "NA1_4316869398": {"time": 1653277065.534, "bot_sums": [[4, 7], [4, 7]], "win_loss": [true, false], "champions": ["Jhin", "Tristana"]}, "NA1_4316944271": {"time": 1653278675.175, "bot_sums": [[4, 7], [4, 7]], "win_loss": [true, false], "champions": ["Jhin", "Twitch"]}, "NA1_4317477903": {"time": 1653341649.434, "bot_sums": [[3, 4], [4, 7]], "win_loss": [false, true], "champions": ["Yone", "Ezreal"]}, "NA1_4317523875": {"time": 1653344319.945, "bot_sums": [[4, 7], [7, 4]], "win_loss": [false, true], "champions": ["Draven", "Ezreal"]}, "NA1_4321252497": {"time": 1653621861.834, "bot_sums": [[4, 3], [4, 7]], "win_loss": [false, true], "champions": ["Ashe", "Vayne"]}, "NA1_4321302572": {"time": 1653625027.183, "bot_sums": [[4, 3], [3, 4]], "win_loss": [false, true], "champions": ["Vayne", "Ashe"]}, "NA1_4321317731": {"time": 1653626627.965, "bot_sums": [[4, 7], [4, 7]], "win_loss": [false, true], "champions": ["Vayne", "Karma"]}, "NA1_4322256385": {"time": 1653712257.164, "bot_sums": [[4, 7], [4, 7]], "win_loss": [false, true], "champions": ["Lucian", "Tristana"]}, "NA1_4323322279": {"time": 1653785601.507, "bot_sums": [[7, 4], [4, 7]], "win_loss": [true, false], "champions": ["Kalista", "Tristana"]}, "NA1_4323318283": {"time": 1653787814.304, "bot_sums": [[7, 4], [4, 7]], "win_loss": [true, false], "champions": ["Kalista", "Ezreal"]}, "NA1_4324571027": {"time": 1653885735.337, "bot_sums": [[7, 4], [4, 3]], "win_loss": [true, false], "champions": ["Draven", "Tristana"]}, "NA1_4330706395": {"time": 1654380520.741, "bot_sums": [[3, 4], [4, 1]], "win_loss": [true, false], "champions": ["Vayne", "Kaisa"]}, "NA1_4330975452": {"time": 1654396424.174, "bot_sums": [[4, 3], [4, 7]], "win_loss": [false, true], "champions": ["Jhin", "Tristana"]}, "NA1_4331021886": {"time": 1654398420.784, "bot_sums": [[7, 4], [4, 7]], "win_loss": [false, true], "champions": ["Jinx", "Tristana"]}, "NA1_4342627108": {"time": 1655249380.239, "bot_sums": [[3, 4], [4, 7]], "win_loss": [false, true], "champions": ["MissFortune", "Tristana"]}, "NA1_4342723671": {"time": 1655252287.614, "bot_sums": [[4, 7], [4, 7]], "win_loss": [true, false], "champions": ["Tristana", "Ezreal"]}, "NA1_4342763416": {"time": 1655255498.394, "bot_sums": [[4, 3], [3, 4]], "win_loss": [false, true], "champions": ["Tristana", "Samira"]}, "NA1_4342800540": {"time": 1655257481.546, "bot_sums": [[7, 4], [4, 7]], "win_loss": [true, false], "champions": ["Jhin", "Tristana"]}, "NA1_4352495359": {"time": 1656035367.759, "bot_sums": [[4, 7], [7, 4]], "win_loss": [true, false], "champions": ["Jhin", "Jinx"]}, "NA1_4352572401": {"time": 1656037710.946, "bot_sums": [[4, 3], [4, 7]], "win_loss": [true, false], "champions": ["Tristana", "Ezreal"]}, "NA1_4352641296": {"time": 1656040608.599, "bot_sums": [[7, 4], [4, 3]], "win_loss": [false, true], "champions": ["Kaisa", "Tristana"]}, "NA1_4352658746": {"time": 1656043081.853, "bot_sums": [[4, 7], [7, 4]], "win_loss": [true, false], "champions": ["Sivir", "Caitlyn"]}, "NA1_4352715646": {"time": 1656045411.057, "bot_sums": [[7, 4], [4, 3]], "win_loss": [true, false], "champions": ["Twitch", "Tristana"]}, "NA1_4352730846": {"time": 1656046979.714, "bot_sums": [[4, 3], [4, 3]], "win_loss": [false, true], "champions": ["Tristana", "Zeri"]}, "NA1_4352735872": {"time": 1656048949.135, "bot_sums": [[4, 3], [4, 7]], "win_loss": [true, false], "champions": ["Tristana", "Jhin"]}, "NA1_4352800397": {"time": 1656051135.3, "bot_sums": [[4, 3], [7, 4]], "win_loss": [true, false], "champions": ["KogMaw", "Jhin"]}, "NA1_4352826407": {"time": 1656054303.311, "bot_sums": [[4, 3], [7, 4]], "win_loss": [false, true], "champions": ["Tristana", "Jinx"]}, "NA1_4353057979": {"time": 1656092555.181, "bot_sums": [[4, 7], [4, 3]], "win_loss": [false, true], "champions": ["Xayah", "Vayne"]}, "NA1_4353141917": {"time": 1656095399.711, "bot_sums": [[7, 4], [4, 3]], "win_loss": [true, false], "champions": ["Draven", "Tristana"]}, "NA1_4353107836": {"time": 1656098527.412, "bot_sums": [[4, 3], [4, 3]], "win_loss": [true, false], "champions": ["Samira", "Ezreal"]}, "NA1_4353171837": {"time": 1656100868.938, "bot_sums": [[4, 3], [1, 4]], "win_loss": [false, true], "champions": ["KogMaw", "Ashe"]}, "NA1_4353155323": {"time": 1656102459.432, "bot_sums": [[4, 3], [3, 4]], "win_loss": [true, false], "champions": ["Vayne", "KogMaw"]}, "NA1_4353561159": {"time": 1656127487.897, "bot_sums": [[3, 4], [4, 1]], "win_loss": [true, false], "champions": ["Ashe", "Vayne"]}, "NA1_4353601987": {"time": 1656130855.398, "bot_sums": [[1, 4], [4, 7]], "win_loss": [true, false], "champions": ["Kaisa", "Tristana"]}, "NA1_4353588138": {"time": 1656132908.441, "bot_sums": [[4, 7], [4, 3]], "win_loss": [false, true], "champions": ["Vayne", "Tristana"]}, "NA1_4353633896": {"time": 1656134934.496, "bot_sums": [[4, 7], [7, 4]], "win_loss": [false, true], "champions": ["Vayne", "Ezreal"]}, "NA1_4353659100": {"time": 1656137459.474, "bot_sums": [[7, 4], [7, 4]], "win_loss": [false, true], "champions": ["Jhin", "Kalista"]}, "NA1_4353696961": {"time": 1656140668.779, "bot_sums": [[4, 3], [7, 4]], "win_loss": [false, true], "champions": ["Swain", "Jhin"]}, "NA1_4353800547": {"time": 1656143629.507, "bot_sums": [[3, 4], [4, 3]], "win_loss": [true, false], "champions": ["Jhin", "Tristana"]}, "NA1_4353966718": {"time": 1656177489.717, "bot_sums": [[7, 4], [4, 3]], "win_loss": [false, true], "champions": ["Jhin", "Tristana"]}, "NA1_4357233657": {"time": 1656454669.015, "bot_sums": [[4, 7], [3, 4]], "win_loss": [true, false], "champions": ["Zeri", "Twitch"]}, "NA1_4357268804": {"time": 1656457172.265, "bot_sums": [[4, 7], [4, 7]], "win_loss": [true, false], "champions": ["Samira", "Zeri"]}, "NA1_4357417908": {"time": 1656467839.507, "bot_sums": [[7, 4], [4, 1]], "win_loss": [false, true], "champions": ["Zeri", "Jhin"]}, "NA1_4357467238": {"time": 1656470594.999, "bot_sums": [[4, 3], [3, 4]], "win_loss": [false, true], "champions": ["KogMaw", "Ashe"]}, "NA1_4357543181": {"time": 1656472740.124, "bot_sums": [[4, 7], [4, 3]], "win_loss": [false, true], "champions": ["Zeri", "Twitch"]}, "NA1_4357549070": {"time": 1656474570.509, "bot_sums": [[4, 7], [4, 21]], "win_loss": [false, true], "champions": ["Zeri", "Twitch"]}, "NA1_4357588974": {"time": 1656477614.714, "bot_sums": [[4, 3], [4, 7]], "win_loss": [true, false], "champions": ["Tristana", "Ashe"]}, "NA1_4357673352": {"time": 1656479643.866, "bot_sums": [[4, 7], [7, 4]], "win_loss": [true, false], "champions": ["Zeri", "Lucian"]}, "NA1_4357711048": {"time": 1656482129.569, "bot_sums": [[4, 7], [4, 3]], "win_loss": [false, true], "champions": ["Zeri", "MissFortune"]}, "NA1_4358258413": {"time": 1656529376.326, "bot_sums": [[4, 3], [7, 4]], "win_loss": [false, true], "champions": ["Zeri", "Jhin"]}, "NA1_4358352830": {"time": 1656532386.022, "bot_sums": [[4, 7], [4, 7]], "win_loss": [false, true], "champions": ["Lucian", "Zeri"]}, "NA1_4358377018": {"time": 1656535048.346, "bot_sums": [[4, 7], [4, 7]], "win_loss": [false, true], "champions": ["Zeri", "Ezreal"]}, "NA1_4358392932": {"time": 1656537685.039, "bot_sums": [[4, 1], [4, 3]], "win_loss": [false, true], "champions": ["Zeri", "Vayne"]}, "NA1_4358437221": {"time": 1656540402.314, "bot_sums": [[4, 3], [7, 4]], "win_loss": [false, true], "champions": ["Zeri", "Samira"]}, "NA1_4358839098": {"time": 1656566998.051, "bot_sums": [[7, 4], [4, 7]], "win_loss": [true, false], "champions": ["Seraphine", "Tristana"]}, "NA1_4359355966": {"time": 1656630519.547, "bot_sums": [[4, 7], [4, 7]], "win_loss": [false, true], "champions": ["Ezreal", "Caitlyn"]}, "NA1_4359494141": {"time": 1656638424.647, "bot_sums": [[4, 3], [4, 14]], "win_loss": [false, true], "champions": ["Tristana", "Lucian"]}, "NA1_4359774672": {"time": 1656656568.202, "bot_sums": [[7, 4], [7, 4]], "win_loss": [true, false], "champions": ["Jhin", "MissFortune"]}, "NA1_4359817105": {"time": 1656658388.412, "bot_sums": [[7, 4], [4, 7]], "win_loss": [false, true], "champions": ["Caitlyn", "Xayah"]}, "NA1_4359861677": {"time": 1656660720.339, "bot_sums": [[7, 4], [4, 7]], "win_loss": [false, true], "champions": ["Kaisa", "Lucian"]}, "NA1_4359845272": {"time": 1656663161.469, "bot_sums": [[7, 4], [7, 4]], "win_loss": [true, false], "champions": ["Lucian", "Kaisa"]}, "NA1_4360126920": {"time": 1656702369.981, "bot_sums": [[4, 7], [4, 7]], "win_loss": [true, false], "champions": ["MissFortune", "Seraphine"]}, "NA1_4360171270": {"time": 1656704681.809, "bot_sums": [[4, 7], [7, 4]], "win_loss": [true, false], "champions": ["Zeri", "Lucian"]}, "NA1_4360385897": {"time": 1656726134.783, "bot_sums": [[7, 4], [4, 7]], "win_loss": [false, true], "champions": ["Twitch", "Zeri"]}, "NA1_4360462376": {"time": 1656728916.25, "bot_sums": [[4, 3], [7, 4]], "win_loss": [true, false], "champions": ["Tristana", "Ziggs"]}, "NA1_4360570141": {"time": 1656735160.801, "bot_sums": [[4, 1], [4, 7]], "win_loss": [false, true], "champions": ["Kaisa", "Zeri"]}, "NA1_4360557831": {"time": 1656737635.123, "bot_sums": [[4, 1], [4, 7]], "win_loss": [false, true], "champions": ["Zeri", "MissFortune"]}, "NA1_4360624220": {"time": 1656740333.724, "bot_sums": [[4, 7], [7, 4]], "win_loss": [false, true], "champions": ["Zeri", "Ezreal"]}, "NA1_4360680276": {"time": 1656742653.103, "bot_sums": [[4, 1], [4, 7]], "win_loss": [false, true], "champions": ["Zeri", "Ashe"]}, "NA1_4361333239": {"time": 1656792235.395, "bot_sums": [[4, 3], [4, 7]], "win_loss": [true, false], "champions": ["Tristana", "Jhin"]}, "NA1_4361327374": {"time": 1656794104.409, "bot_sums": [[4, 3], [7, 4]], "win_loss": [true, false], "champions": ["Tristana", "Jhin"]}, "NA1_4361371158": {"time": 1656796092.268, "bot_sums": [[4, 3], [4, 3]], "win_loss": [true, false], "champions": ["Aphelios", "Tristana"]}, "NA1_4362217203": {"time": 1656880291.155, "bot_sums": [[3, 4], [4, 7]], "win_loss": [false, true], "champions": ["Draven", "Tristana"]}, "NA1_4362281648": {"time": 1656882600.418, "bot_sums": [[4, 1], [4, 7]], "win_loss": [true, false], "champions": ["Draven", "MissFortune"]}, "NA1_4362438823": {"time": 1656896043.095, "bot_sums": [[4, 7], [21, 14]], "win_loss": [false, true], "champions": ["Zeri", "Rengar"]}, "NA1_4362485630": {"time": 1656898648.315, "bot_sums": [[7, 4], [4, 7]], "win_loss": [false, true], "champions": ["Jinx", "Caitlyn"]}, "NA1_4363144763": {"time": 1656963527.183, "bot_sums": [[4, 3], [12, 4]], "win_loss": [true, false], "champions": ["Tristana", "Swain"]}, "NA1_4363118640": {"time": 1656964930.979, "bot_sums": [[7, 4], [4, 7]], "win_loss": [false, true], "champions": ["Kaisa", "Zeri"]}, "NA1_4363182748": {"time": 1656966928.292, "bot_sums": [[4, 7], [12, 4]], "win_loss": [true, false], "champions": ["Zeri", "Ziggs"]}, "NA1_4363248198": {"time": 1656974189.609, "bot_sums": [[4, 7], [4, 7]], "win_loss": [false, true], "champions": ["KogMaw", "Zeri"]}, "NA1_4363313827": {"time": 1656977049.415, "bot_sums": [[4, 1], [4, 7]], "win_loss": [false, true], "champions": ["Jinx", "Zeri"]}, "NA1_4363337344": {"time": 1656978882.337, "bot_sums": [[4, 7], [7, 4]], "win_loss": [true, false], "champions": ["Zeri", "Twitch"]}, "NA1_4363689372": {"time": 1657003971.662, "bot_sums": [[4, 3], [4, 7]], "win_loss": [false, true], "champions": ["MissFortune", "Zeri"]}, "NA1_4363711475": {"time": 1657004568.325, "bot_sums": [[4, 7], [7, 4]], "win_loss": [false, true], "champions": ["Zeri", "Ezreal"]}, "NA1_4364761607": {"time": 1657079999.073, "bot_sums": [[4, 7], [7, 4]], "win_loss": [true, false], "champions": ["Zeri", "KogMaw"]}, "NA1_4364739403": {"time": 1657082297.684, "bot_sums": [[4, 12], [4, 7]], "win_loss": [false, true], "champions": ["Veigar", "Zeri"]}, "NA1_4364776340": {"time": 1657084709.215, "bot_sums": [[4, 7], [7, 4]], "win_loss": [true, false], "champions": ["Zeri", "Ezreal"]}, "NA1_4364808811": {"time": 1657086288.186, "bot_sums": [[4, 1], [4, 3]], "win_loss": [false, true], "champions": ["Zeri", "Samira"]}, "NA1_4364854287": {"time": 1657088719.429, "bot_sums": [[3, 4], [4, 1]], "win_loss": [true, false], "champions": ["Kalista", "Zeri"]}, "NA1_4365183978": {"time": 1657135011.49, "bot_sums": [[4, 1], [7, 4]], "win_loss": [false, true], "champions": ["Zeri", "Ashe"]}, "NA1_4365178807": {"time": 1657137403.586, "bot_sums": [[4, 7], [7, 4]], "win_loss": [true, false], "champions": ["Zeri", "Twitch"]}, "NA1_4365222618": {"time": 1657139590.606, "bot_sums": [[4, 7], [7, 4]], "win_loss": [false, true], "champions": ["Zeri", "Kaisa"]}, "NA1_4365236353": {"time": 1657141647.006, "bot_sums": [[4, 3], [4, 1]], "win_loss": [true, false], "champions": ["Vayne", "Zeri"]}, "NA1_4365260307": {"time": 1657143280.778, "bot_sums": [[3, 4], [7, 4]], "win_loss": [false, true], "champions": ["Ashe", "Jinx"]}, "NA1_4365265335": {"time": 1657145933.834, "bot_sums": [[4, 7], [4, 7]], "win_loss": [false, true], "champions": ["Twitch", "Jhin"]}, "NA1_4365299222": {"time": 1657148374.067, "bot_sums": [[4, 14], [7, 4]], "win_loss": [true, false], "champions": ["Yasuo", "Ashe"]}, "NA1_4365328093": {"time": 1657151921.242, "bot_sums": [[4, 7], [4, 7]], "win_loss": [false, true], "champions": ["Jhin", "Kaisa"]}, "NA1_4365372971": {"time": 1657153730.728, "bot_sums": [[4, 7], [3, 4]], "win_loss": [false, true], "champions": ["Lucian", "Zeri"]}, "NA1_4366064338": {"time": 1657223924.994, "bot_sums": [[4, 3], [3, 4]], "win_loss": [true, false], "champions": ["Tristana", "Lucian"]}, "NA1_4366048240": {"time": 1657225797.779, "bot_sums": [[3, 4], [4, 7]], "win_loss": [true, false], "champions": ["Caitlyn", "Zeri"]}, "NA1_4366123835": {"time": 1657229252.446, "bot_sums": [[4, 3], [4, 3]], "win_loss": [true, false], "champions": ["Vayne", "Ezreal"]}, "NA1_4366118461": {"time": 1657231671.663, "bot_sums": [[4, 7], [7, 4]], "win_loss": [false, true], "champions": ["Zeri", "Ezreal"]}, "NA1_4367410516": {"time": 1657334802.336, "bot_sums": [[4, 14], [4, 7]], "win_loss": [false, true], "champions": ["Twitch", "Tristana"]}, "NA1_4367458483": {"time": 1657337568.692, "bot_sums": [[4, 1], [4, 3]], "win_loss": [true, false], "champions": ["Tristana", "Ezreal"]}, "NA1_4367516639": {"time": 1657339662.074, "bot_sums": [[4, 7], [4, 7]], "win_loss": [false, true], "champions": ["Ezreal", "Zeri"]}, "NA1_4367612428": {"time": 1657341637.124, "bot_sums": [[7, 4], [4, 7]], "win_loss": [false, true], "champions": ["Kalista", "Zeri"]}, "NA1_4367627586": {"time": 1657343802.103, "bot_sums": [[7, 4], [4, 7]], "win_loss": [true, false], "champions": ["Jhin", "Tristana"]}, "NA1_4367685782": {"time": 1657346522.453, "bot_sums": [[1, 4], [4, 3]], "win_loss": [false, true], "champions": ["Samira", "Tristana"]}, "NA1_4367760813": {"time": 1657349248.826, "bot_sums": [[4, 3], [4, 3]], "win_loss": [false, true], "champions": ["Draven", "Tristana"]}, "NA1_4367773236": {"time": 1657350494.02, "bot_sums": [[7, 4], [4, 7]], "win_loss": [true, false], "champions": ["Jinx", "Zeri"]}, "NA1_4367757709": {"time": 1657352773.046, "bot_sums": [[7, 4], [4, 7]], "win_loss": [false, true], "champions": ["Jinx", "Zeri"]}, "NA1_4367830580": {"time": 1657355129.787, "bot_sums": [[4, 7], [4, 3]], "win_loss": [true, false], "champions": ["Zeri", "Varus"]}, "NA1_4368585982": {"time": 1657431057.676, "bot_sums": [[4, 3], [4, 1]], "win_loss": [false, true], "champions": ["Jhin", "Samira"]}, "NA1_4368628918": {"time": 1657432755.883, "bot_sums": [[4, 3], [4, 3]], "win_loss": [true, false], "champions": ["Tristana", "Vayne"]}, "NA1_4368663286": {"time": 1657434565.899, "bot_sums": [[4, 3], [14, 4]], "win_loss": [true, false], "champions": ["Zeri", "Twitch"]}, "NA1_4368668858": {"time": 1657437356.893, "bot_sums": [[4, 7], [4, 1]], "win_loss": [false, true], "champions": ["Varus", "Zeri"]}, "NA1_4368743020": {"time": 1657439930.461, "bot_sums": [[4, 7], [7, 4]], "win_loss": [false, true], "champions": ["Zeri", "Lucian"]}, "NA1_4368736379": {"time": 1657442249.32, "bot_sums": [[3, 4], [4, 1]], "win_loss": [false, true], "champions": ["Samira", "Zeri"]}, "NA1_4368779927": {"time": 1657445098.347, "bot_sums": [[4, 7], [4, 7]], "win_loss": [false, true], "champions": ["Zeri", "Caitlyn"]}, "NA1_4369010855": {"time": 1657479537.664, "bot_sums": [[4, 7], [4, 7]], "win_loss": [true, false], "champions": ["Zeri", "Jhin"]}, "NA1_4369005655": {"time": 1657481495.109, "bot_sums": [[4, 7], [4, 7]], "win_loss": [false, true], "champions": ["Zeri", "Twitch"]}, "NA1_4369513065": {"time": 1657512086.404, "bot_sums": [[4, 7], [4, 7]], "win_loss": [true, false], "champions": ["Caitlyn", "Zeri"]}, "NA1_4369590557": {"time": 1657514813.415, "bot_sums": [[4, 7], [4, 3]], "win_loss": [true, false], "champions": ["Zeri", "Samira"]}, "NA1_4369585976": {"time": 1657516919.39, "bot_sums": [[7, 4], [4, 7]], "win_loss": [false, true], "champions": ["Ashe", "Zeri"]}, "NA1_4369652381": {"time": 1657519894.857, "bot_sums": [[3, 4], [4, 7]], "win_loss": [false, true], "champions": ["Vayne", "Zeri"]}, "NA1_4369619036": {"time": 1657522699.593, "bot_sums": [[4, 1], [4, 1]], "win_loss": [true, false], "champions": ["Zeri", "Kalista"]}, "NA1_4369680061": {"time": 1657523998.394, "bot_sums": [[4, 7], [4, 7]], "win_loss": [true, false], "champions": ["Ezreal", "Zeri"]}, "NA1_4369675317": {"time": 1657527116.361, "bot_sums": [[4, 7], [7, 4]], "win_loss": [true, false], "champions": ["Zeri", "Jhin"]}, "NA1_4371026540": {"time": 1657644237.179, "bot_sums": [[4, 1], [4, 7]], "win_loss": [false, true], "champions": ["Ezreal", "Zeri"]}, "NA1_4371029716": {"time": 1657646544.056, "bot_sums": [[4, 7], [3, 4]], "win_loss": [true, false], "champions": ["Zeri", "Lucian"]}, "NA1_4371073581": {"time": 1657648297.036, "bot_sums": [[4, 7], [4, 7]], "win_loss": [false, true], "champions": ["Zeri", "Sivir"]}, "NA1_4371105439": {"time": 1657650334.054, "bot_sums": [[4, 7], [4, 7]], "win_loss": [false, true], "champions": ["Caitlyn", "Zeri"]}, "NA1_4371119139": {"time": 1657653037.452, "bot_sums": [[4, 7], [4, 3]], "win_loss": [false, true], "champions": ["Jinx", "Zeri"]}, "NA1_4371153683": {"time": 1657655344.054, "bot_sums": [[4, 7], [4, 7]], "win_loss": [false, true], "champions": ["Jhin", "Zeri"]}, "NA1_4371166019": {"time": 1657656930.541, "bot_sums": [[4, 7], [4, 7]], "win_loss": [false, true], "champions": ["Kaisa", "Zeri"]}, "NA1_4371176721": {"time": 1657657435.228, "bot_sums": [[4, 7], [7, 4]], "win_loss": [false, true], "champions": ["Zeri", "Aphelios"]}, "NA1_4371149613": {"time": 1657658499.045, "bot_sums": [[4, 7], [3, 4]], "win_loss": [false, true], "champions": ["Zeri", "Vayne"]}, "NA1_4372424803": {"time": 1657752729.418, "bot_sums": [[3, 4], [4, 7]], "win_loss": [false, true], "champions": ["Nilah", "Zeri"]}, "NA1_4372510697": {"time": 1657755243.364, "bot_sums": [[4, 7], [4, 7]], "win_loss": [true, false], "champions": ["Sivir", "Zeri"]}, "NA1_4373294200": {"time": 1657831501.438, "bot_sums": [[4, 7], [7, 4]], "win_loss": [false, true], "champions": ["Zeri", "Kaisa"]}, "NA1_4373319229": {"time": 1657834054.817, "bot_sums": [[4, 3], [4, 3]], "win_loss": [true, false], "champions": ["Zeri", "Tristana"]}, "NA1_4373337527": {"time": 1657837203.628, "bot_sums": [[3, 4], [4, 7]], "win_loss": [true, false], "champions": ["Sivir", "Zeri"]}, "NA1_4426412411": {"time": 1662351097.464, "bot_sums": [[7, 4], [6, 4]], "win_loss": [false, true], "champions": ["Kaisa", "Zeri"]}, "NA1_4426419121": {"time": 1662353378.975, "bot_sums": [[4, 7], [7, 4]], "win_loss": [false, true], "champions": ["Jhin", "Nilah"]}, "NA1_4453126306": {"time": 1664741181.553, "bot_sums": [[7, 4], [7, 4]], "win_loss": [false, true], "champions": ["Jinx", "Nilah"]}, "NA1_4453162654": {"time": 1664744183.518, "bot_sums": [[4, 7], [7, 4]], "win_loss": [false, true], "champions": ["Caitlyn", "Nilah"]}, "NA1_4500639821": {"time": 1669258398.45, "bot_sums": [[4, 7], [7, 4]], "win_loss": [true, false], "champions": ["Lucian", "Ezreal"]}, "NA1_4500665622": {"time": 1669260614.235, "bot_sums": [[4, 7], [4, 7]], "win_loss": [true, false], "champions": ["Twitch", "Zeri"]}, "NA1_4516030015": {"time": 1670805407.09, "bot_sums": [[7, 4], [4, 7]], "win_loss": [true, false], "champions": ["MissFortune", "Zeri"]}, "NA1_4527031081": {"time": 1671813161.904, "bot_sums": [[21, 4], [3, 4]], "win_loss": [true, false], "champions": ["Jhin", "Tristana"]}, "NA1_4527647145": {"time": 1671858474.15, "bot_sums": [[4, 7], [4, 7]], "win_loss": [false, true], "champions": ["Caitlyn", "Kaisa"]}, "NA1_4536362041": {"time": 1672680085.808, "bot_sums": [[4, 7], [4, 7]], "win_loss": [false, true], "champions": ["Jhin", "Ezreal"]}, "NA1_4536382104": {"time": 1672682323.6, "bot_sums": [[4, 3], [4, 7]], "win_loss": [true, false], "champions": ["Caitlyn", "Ezreal"]}, "NA1_4536404755": {"time": 1672684600.832, "bot_sums": [[4, 3], [4, 3]], "win_loss": [true, false], "champions": ["Kaisa", "Lucian"]}, "NA1_4541986986": {"time": 1673204193.068, "bot_sums": [[1, 4], [14, 4]], "win_loss": [true, false], "champions": ["Kaisa", "Yasuo"]}, "NA1_4542004033": {"time": 1673206171.371, "bot_sums": [[7, 4], [4, 7]], "win_loss": [true, false], "champions": ["Kaisa", "Jhin"]}, "NA1_4555187888": {"time": 1674348527.371, "bot_sums": [[7, 4], [3, 4]], "win_loss": [true, false], "champions": ["Vayne", "Karthus"]}, "NA1_4555214317": {"time": 1674350470.429, "bot_sums": [[3, 4], [4, 7]], "win_loss": [true, false], "champions": ["Jinx", "Nilah"]}, "NA1_4555259410": {"time": 1674353088.927, "bot_sums": [[4, 1], [4, 6]], "win_loss": [true, false], "champions": ["Kaisa", "Zeri"]}, "NA1_4555288675": {"time": 1674354973.837, "bot_sums": [[4, 7], [4, 7]], "win_loss": [false, true], "champions": ["Draven", "Jhin"]}, "NA1_4556248523": {"time": 1674433794.669, "bot_sums": [[4, 7], [4, 7]], "win_loss": [false, true], "champions": ["Kaisa", "Ezreal"]}, "NA1_4556295090": {"time": 1674435961.805, "bot_sums": [[4, 7], [4, 7]], "win_loss": [true, false], "champions": ["Tristana", "Ezreal"]}, "NA1_4561874165": {"time": 1674946557.598, "bot_sums": [[4, 3], [4, 7]], "win_loss": [true, false], "champions": ["Twitch", "Ezreal"]}, "NA1_4561931128": {"time": 1674950468.065, "bot_sums": [[1, 4], [4, 7]], "win_loss": [false, true], "champions": ["Varus", "Ezreal"]}, "NA1_4561967853": {"time": 1674952845.018, "bot_sums": [[3, 4], [3, 4]], "win_loss": [false, true], "champions": ["Samira", "Swain"]}, "NA1_4561992349": {"time": 1674954614.619, "bot_sums": [[4, 3], [4, 7]], "win_loss": [true, false], "champions": ["Lucian", "Kaisa"]}, "NA1_4562208499": {"time": 1674966358.971, "bot_sums": [[4, 7], [7, 4]], "win_loss": [false, true], "champions": ["Jhin", "Ezreal"]}, "NA1_4562273371": {"time": 1674969358.652, "bot_sums": [[3, 4], [3, 4]], "win_loss": [false, true], "champions": ["Draven", "Ezreal"]}, "NA1_4568351726": {"time": 1675530922.563, "bot_sums": [[4, 7], [4, 1]], "win_loss": [false, true], "champions": ["Xayah", "Tristana"]}, "NA1_4569531771": {"time": 1675629367.838, "bot_sums": [[4, 7], [1, 4]], "win_loss": [true, false], "champions": ["Jhin", "Kaisa"]}, "NA1_4569562019": {"time": 1675631744.412, "bot_sums": [[7, 4], [6, 4]], "win_loss": [false, true], "champions": ["Kaisa", "Zeri"]}, "NA1_4569595207": {"time": 1675634172.522, "bot_sums": [[6, 4], [1, 4]], "win_loss": [true, false], "champions": ["Jhin", "Kaisa"]}, "NA1_4569615698": {"time": 1675636068.028, "bot_sums": [[7, 4], [1, 4]], "win_loss": [false, true], "champions": ["Kaisa", "Caitlyn"]}, "NA1_4575805913": {"time": 1676229681.967, "bot_sums": [[7, 4], [4, 7]], "win_loss": [false, true], "champions": ["Kaisa", "Sivir"]}}